colorfill/__init__.py
colorfill/test.py
colorfill-1.0.dist-info/METADATA
colorfill-1.0.dist-info/WHEEL
colorfill-1.0.dist-info/top_level.txt
colorfill-1.0.dist-info/RECORD
