Metadata-Version: 2.1
Name: colorfill
Version: 1.0
Summary: python library for colors
Author-email: yktony@gmail.com
License: Eclipse Public License 2.0
